MANIFEST.in
setup.py
src/jld_scripts/__init__.py
src/jld_scripts.egg-info/PKG-INFO
src/jld_scripts.egg-info/SOURCES.txt
src/jld_scripts.egg-info/dependency_links.txt
src/jld_scripts.egg-info/not-zip-safe
src/jld_scripts.egg-info/top_level.txt
src/jld_scripts/agents/__init__.py
src/jld_scripts/agents/clock.py
src/jld_scripts/agents/mk_dbus.py
src/jld_scripts/agents/notifier.py
src/jld_scripts/agents/squeeze.py
src/jld_scripts/agents/squeeze_tray.py
src/jld_scripts/agents/tray.py
src/jld_scripts/agents/watcher.py
src/jld_scripts/agents/watcher_dbus.py
src/jld_scripts/music/__init__.py
src/jld_scripts/music/id3.py
src/jld_scripts/music/m3ufile.py
src/jld_scripts/music/mp3file.py
src/jld_scripts/music/lastfm/__init__.py
src/jld_scripts/music/lastfm/base.py
src/jld_scripts/music/lastfm/parser_gettracks.py
src/jld_scripts/res/__init__.py
src/jld_scripts/res/squeezecenter.gif
src/jld_scripts/scripts/__init__.py
src/jld_scripts/scripts/id3info.py
src/jld_scripts/scripts/lastfm_gettracks.py
src/jld_scripts/scripts/m3u2symlinks.py
src/jld_scripts/scripts/squeezecenter_utils.py
src/jld_scripts/scripts/watcher.py
src/jld_scripts/system/__init__.py
src/jld_scripts/system/base.py
src/jld_scripts/system/db.py
src/jld_scripts/system/logger.py
src/jld_scripts/system/messaging.py
src/jld_scripts/system/mos.py
src/jld_scripts/system/mswitch.py
src/jld_scripts/system/oparser.py
src/jld_scripts/system/path.py
src/jld_scripts/system/state.py
src/jld_scripts/system/ui_base.py
src/scripts/id3info
src/scripts/lastfm_gettracks
src/scripts/m3u2symlinks
src/scripts/squeezecenter_utils