Metadata-Version: 1.0
Name: jld-scripts
Version: 0.8.7
Summary: Collection of python utility scripts
Home-page: http://www.systemical.com/doc/opensource/jld_scripts
Author: Jean-Lou Dupont
Author-email: jl@jldupont.com
License: UNKNOWN
Platform: UNKNOWN
